MANIFEST.in
README.rst
setup.py
app_metrics/__init__.py
app_metrics/admin.py
app_metrics/exceptions.py
app_metrics/models.py
app_metrics/reports.py
app_metrics/tasks.py
app_metrics/trending.py
app_metrics/urls.py
app_metrics/utils.py
app_metrics/views.py
app_metrics/backends/__init__.py
app_metrics/backends/composite.py
app_metrics/backends/db.py
app_metrics/backends/librato.py
app_metrics/backends/mixpanel.py
app_metrics/backends/redis.py
app_metrics/backends/statsd.py
app_metrics/management/__init__.py
app_metrics/management/commands/__init__.py
app_metrics/management/commands/metrics_aggregate.py
app_metrics/management/commands/metrics_send_mail.py
app_metrics/management/commands/move_to_mixpanel.py
app_metrics/management/commands/move_to_statsd.py
app_metrics/migrations/0001_initial.py
app_metrics/migrations/0002_alter_created_to_datetime.py
app_metrics/migrations/0003_auto__add_gauge.py
app_metrics/migrations/__init__.py
app_metrics/templates/500.html
app_metrics/templates/admin/app_metrics/app_index.html
app_metrics/templates/app_metrics/email.html
app_metrics/templates/app_metrics/email.txt
app_metrics/templates/app_metrics/reports.html
app_metrics/tests/__init__.py
app_metrics/tests/base_tests.py
app_metrics/tests/librato_tests.py
app_metrics/tests/mixpanel_tests.py
app_metrics/tests/redis_tests.py
app_metrics/tests/settings.py
app_metrics/tests/statsd_tests.py
app_metrics/tests/urls.py
django_app_metrics.egg-info/PKG-INFO
django_app_metrics.egg-info/SOURCES.txt
django_app_metrics.egg-info/dependency_links.txt
django_app_metrics.egg-info/requires.txt
django_app_metrics.egg-info/top_level.txt