Metadata-Version: 1.0
Name: django-app-metrics
Version: 0.8.0
Summary: django-app-metrics is a reusable Django application for tracking and emailing application metrics.
Home-page: https://github.com/frankwiles/django-app-metrics
Author: Frank Wiles
Author-email: frank@revsys.com
License: UNKNOWN
Platform: UNKNOWN
Classifier: Development Status :: 4 - Beta
Classifier: Environment :: Web Environment
Classifier: Intended Audience :: Developers
Classifier: License :: OSI Approved :: BSD License
Classifier: Operating System :: OS Independent
Classifier: Programming Language :: Python
Classifier: Framework :: Django
